Color_Console/Color_Console.py
Color_Console/__init__.py
Color_Console/setup.py
ConsoleColorText-10.0.dist-info/METADATA
ConsoleColorText-10.0.dist-info/WHEEL
ConsoleColorText-10.0.dist-info/top_level.txt
ConsoleColorText-10.0.dist-info/RECORD
